circles_local_aws_s3_storage_python/AWSStorage.py
circles_local_aws_s3_storage_python/CirclesStorage.py
circles_local_aws_s3_storage_python/FileTypeDB.py
circles_local_aws_s3_storage_python/StorageDB.py
circles_local_aws_s3_storage_python/StorageInterface.py
circles_local_aws_s3_storage_python/__init__.py
circles_local_aws_s3_storage_python/constants.py
tests/__init__.py
tests/test_S3.py
tests/test_circles_storage.py
CirclesS3Storage-0.1.1.dist-info/METADATA
CirclesS3Storage-0.1.1.dist-info/WHEEL
CirclesS3Storage-0.1.1.dist-info/top_level.txt
CirclesS3Storage-0.1.1.dist-info/RECORD
