Metadata-Version: 2.1
Name: CirclesS3Storage
Version: 0.1.1
Summary: PyPI Package for Circles Storage functions
Home-page: https://github.com/javatechy/dokr
Author: Circles
Author-email: info@circle.zone
Classifier: Programming Language :: Python :: 3
Classifier: License :: Other/Proprietary License
Classifier: Operating System :: OS Independent
